metricq_sink_nsca/__init__.py
metricq_sink_nsca/check.py
metricq_sink_nsca/logging.py
metricq_sink_nsca/main.py
metricq_sink_nsca/override.py
metricq_sink_nsca/plugin.py
metricq_sink_nsca/report_queue.py
metricq_sink_nsca/reporter.py
metricq_sink_nsca/state.py
metricq_sink_nsca/state_cache.py
metricq_sink_nsca/subtask.py
metricq_sink_nsca/timeout_check.py
metricq_sink_nsca/value_check.py
metricq_sink_nsca/version.py
metricq_sink_nsca-1.8.3.dist-info/LICENSE.txt
metricq_sink_nsca-1.8.3.dist-info/METADATA
metricq_sink_nsca-1.8.3.dist-info/WHEEL
metricq_sink_nsca-1.8.3.dist-info/entry_points.txt
metricq_sink_nsca-1.8.3.dist-info/top_level.txt
metricq_sink_nsca-1.8.3.dist-info/RECORD
