Metadata-Version: 2.1
Name: metricq-sink-nsca
Version: 1.8.3
Author: TU Dresden
Author-email: philipp.joram@tu-dresden.de
License: GPL3
Requires-Python: >=3.10
License-File: LICENSE.txt
Requires-Dist: metricq (~=4.0)
Requires-Dist: click (~=8.0)
Requires-Dist: click-log (~=0.3)
Provides-Extra: dev
Requires-Dist: pytest ; extra == 'dev'
Requires-Dist: pytest-asyncio ; extra == 'dev'
Requires-Dist: black ; extra == 'dev'
Requires-Dist: check-manifest ; extra == 'dev'
Requires-Dist: flake8 (~=3.8) ; extra == 'dev'
Requires-Dist: flake8-bugbear ; extra == 'dev'
Requires-Dist: isort (~=5.0) ; extra == 'dev'
Requires-Dist: pre-commit ; extra == 'dev'
Requires-Dist: sphinx (~=4.2) ; extra == 'dev'
Requires-Dist: sphinx-rtd-theme (~=0.4.3) ; extra == 'dev'
Requires-Dist: sphinx-autodoc-typehints (~=1.10) ; extra == 'dev'
Requires-Dist: sphinxcontrib-spelling (~=5.4) ; extra == 'dev'
Requires-Dist: releases (~=1.6) ; extra == 'dev'
Requires-Dist: tox ; extra == 'dev'
Provides-Extra: docs
Requires-Dist: sphinx (~=4.2) ; extra == 'docs'
Requires-Dist: sphinx-rtd-theme (~=0.4.3) ; extra == 'docs'
Requires-Dist: sphinx-autodoc-typehints (~=1.10) ; extra == 'docs'
Requires-Dist: sphinxcontrib-spelling (~=5.4) ; extra == 'docs'
Requires-Dist: releases (~=1.6) ; extra == 'docs'
Provides-Extra: lint
Requires-Dist: black ; extra == 'lint'
Requires-Dist: check-manifest ; extra == 'lint'
Requires-Dist: flake8 (~=3.8) ; extra == 'lint'
Requires-Dist: flake8-bugbear ; extra == 'lint'
Requires-Dist: isort (~=5.0) ; extra == 'lint'
Requires-Dist: pre-commit ; extra == 'lint'
Provides-Extra: test
Requires-Dist: pytest ; extra == 'test'
Requires-Dist: pytest-asyncio ; extra == 'test'
Provides-Extra: uvloop
Requires-Dist: uvloop (~=0.15.2) ; extra == 'uvloop'
